{"version":3,"scope":"design-system+storybook","description":"Per primitive: transitive var() resolution (tokens + variables + all css/src). Totals = implementation files + Storybook story files (no overlap).","generatedAt":"2026-04-11T20:40:58.048Z","repoRevision":"f74963e53ae3db58b732314df887329d6ff01eb6","scan":{"implementationRoots":["design-system/core","design-system/css/src"],"implementationFileCount":584,"storyFileCount":717,"cssDefinitionFilesMerged":107},"thresholds":{"highMinPercentile":66,"lowMaxPercentile":33,"highMinCount":10,"lowMaxCount":3},"primitives":{"--color-black":{"total":0,"fromImplementation":0,"fromStorybook":0,"aliases":[]},"--color-blue-100":{"total":24,"fromImplementation":24,"fromStorybook":0,"aliases":["--primary-ultra-light"]},"--color-blue-1000":{"total":102,"fromImplementation":101,"fromStorybook":1,"aliases":["--jal","--primary","--primary-shadow","--text-link"]},"--color-blue-1000-12a":{"total":0,"fromImplementation":0,"fromStorybook":0,"aliases":[]},"--color-blue-1000-16a":{"total":0,"fromImplementation":0,"fromStorybook":0,"aliases":[]},"--color-blue-1000-4a":{"total":0,"fromImplementation":0,"fromStorybook":0,"aliases":[]},"--color-blue-1100":{"total":0,"fromImplementation":0,"fromStorybook":0,"aliases":[]},"--color-blue-1200":{"total":129,"fromImplementation":129,"fromStorybook":0,"aliases":["--jal-dark","--primary-dark","--primary-focus"]},"--color-blue-1200-16a":{"total":0,"fromImplementation":0,"fromStorybook":0,"aliases":[]},"--color-blue-1300":{"total":39,"fromImplementation":37,"fromStorybook":2,"aliases":["--jal-darker","--primary-darker"]},"--color-blue-1400":{"total":0,"fromImplementation":0,"fromStorybook":0,"aliases":[]},"--color-blue-200":{"total":32,"fromImplementation":32,"fromStorybook":0,"aliases":["--jal-lightest","--primary-lightest"]},"--color-blue-200-48a":{"total":0,"fromImplementation":0,"fromStorybook":0,"aliases":[]},"--color-blue-300":{"total":1,"fromImplementation":1,"fromStorybook":0,"aliases":["--primary-300"]},"--color-blue-400":{"total":0,"fromImplementation":0,"fromStorybook":0,"aliases":[]},"--color-blue-500":{"total":39,"fromImplementation":39,"fromStorybook":0,"aliases":["--jal-lighter","--primary-lighter"]},"--color-blue-500-48a":{"total":0,"fromImplementation":0,"fromStorybook":0,"aliases":[]},"--color-blue-600":{"total":0,"fromImplementation":0,"fromStorybook":0,"aliases":[]},"--color-blue-700":{"total":6,"fromImplementation":6,"fromStorybook":0,"aliases":["--jal-light","--primary-light"]},"--color-blue-800":{"total":0,"fromImplementation":0,"fromStorybook":0,"aliases":[]},"--color-blue-900":{"total":0,"fromImplementation":0,"fromStorybook":0,"aliases":[]},"--color-cyan-100":{"total":0,"fromImplementation":0,"fromStorybook":0,"aliases":[]},"--color-cyan-1000":{"total":0,"fromImplementation":0,"fromStorybook":0,"aliases":[]},"--color-cyan-1100":{"total":0,"fromImplementation":0,"fromStorybook":0,"aliases":[]},"--color-cyan-1200":{"total":0,"fromImplementation":0,"fromStorybook":0,"aliases":[]},"--color-cyan-1300":{"total":0,"fromImplementation":0,"fromStorybook":0,"aliases":[]},"--color-cyan-1400":{"total":0,"fromImplementation":0,"fromStorybook":0,"aliases":[]},"--color-cyan-200":{"total":0,"fromImplementation":0,"fromStorybook":0,"aliases":[]},"--color-cyan-300":{"total":0,"fromImplementation":0,"fromStorybook":0,"aliases":[]},"--color-cyan-400":{"total":0,"fromImplementation":0,"fromStorybook":0,"aliases":[]},"--color-cyan-500":{"total":0,"fromImplementation":0,"fromStorybook":0,"aliases":[]},"--color-cyan-600":{"total":0,"fromImplementation":0,"fromStorybook":0,"aliases":[]},"--color-cyan-700":{"total":0,"fromImplementation":0,"fromStorybook":0,"aliases":[]},"--color-cyan-800":{"total":0,"fromImplementation":0,"fromStorybook":0,"aliases":[]},"--color-cyan-900":{"total":0,"fromImplementation":0,"fromStorybook":0,"aliases":[]},"--color-gray-100":{"total":50,"fromImplementation":35,"fromStorybook":15,"aliases":["--secondary-lightest","--stone-lightest"]},"--color-gray-100-40a":{"total":0,"fromImplementation":0,"fromStorybook":0,"aliases":[]},"--color-gray-1000":{"total":0,"fromImplementation":0,"fromStorybook":0,"aliases":[]},"--color-gray-1100":{"total":15,"fromImplementation":15,"fromStorybook":0,"aliases":["--inverse-light","--night-light"]},"--color-gray-1200":{"total":0,"fromImplementation":0,"fromStorybook":0,"aliases":[]},"--color-gray-1300":{"total":0,"fromImplementation":0,"fromStorybook":0,"aliases":[]},"--color-gray-1400":{"total":62,"fromImplementation":61,"fromStorybook":1,"aliases":["--inverse","--inverse-focus","--inverse-shadow","--night","--text"]},"--color-gray-1400-16a":{"total":0,"fromImplementation":0,"fromStorybook":0,"aliases":[]},"--color-gray-1400-48a":{"total":0,"fromImplementation":0,"fromStorybook":0,"aliases":[]},"--color-gray-1400-64a":{"total":0,"fromImplementation":0,"fromStorybook":0,"aliases":[]},"--color-gray-1400-80a":{"total":0,"fromImplementation":0,"fromStorybook":0,"aliases":[]},"--color-gray-200":{"total":37,"fromImplementation":36,"fromStorybook":1,"aliases":["--secondary-lighter","--stone-lighter"]},"--color-gray-300":{"total":60,"fromImplementation":60,"fromStorybook":0,"aliases":["--secondary-light","--stone-light"]},"--color-gray-400":{"total":113,"fromImplementation":107,"fromStorybook":6,"aliases":["--border","--border-s","--secondary","--secondary-shadow","--stone"]},"--color-gray-400-16a":{"total":0,"fromImplementation":0,"fromStorybook":0,"aliases":[]},"--color-gray-500":{"total":55,"fromImplementation":49,"fromStorybook":6,"aliases":["--secondary-dark","--stone-dark"]},"--color-gray-600":{"total":0,"fromImplementation":0,"fromStorybook":0,"aliases":[]},"--color-gray-700":{"total":34,"fromImplementation":34,"fromStorybook":0,"aliases":["--inverse-lightest","--night-lightest","--text-disabled"]},"--color-gray-800":{"total":0,"fromImplementation":0,"fromStorybook":0,"aliases":[]},"--color-gray-900":{"total":27,"fromImplementation":27,"fromStorybook":0,"aliases":["--inverse-lighter","--night-lighter","--text-subtle"]},"--color-green-100":{"total":1,"fromImplementation":1,"fromStorybook":0,"aliases":["--success-ultra-light"]},"--color-green-1000":{"total":40,"fromImplementation":39,"fromStorybook":1,"aliases":["--neem","--success","--success-shadow","--text-success"]},"--color-green-1000-16a":{"total":0,"fromImplementation":0,"fromStorybook":0,"aliases":[]},"--color-green-1000-4a":{"total":0,"fromImplementation":0,"fromStorybook":0,"aliases":[]},"--color-green-1100":{"total":0,"fromImplementation":0,"fromStorybook":0,"aliases":[]},"--color-green-1200":{"total":5,"fromImplementation":5,"fromStorybook":0,"aliases":["--neem-dark","--success-dark"]},"--color-green-1200-16a":{"total":0,"fromImplementation":0,"fromStorybook":0,"aliases":[]},"--color-green-1300":{"total":7,"fromImplementation":7,"fromStorybook":0,"aliases":["--neem-darker","--success-darker"]},"--color-green-1400":{"total":0,"fromImplementation":0,"fromStorybook":0,"aliases":[]},"--color-green-200":{"total":4,"fromImplementation":4,"fromStorybook":0,"aliases":["--neem-lightest","--success-lightest"]},"--color-green-300":{"total":1,"fromImplementation":1,"fromStorybook":0,"aliases":["--success-300"]},"--color-green-400":{"total":0,"fromImplementation":0,"fromStorybook":0,"aliases":[]},"--color-green-500":{"total":3,"fromImplementation":3,"fromStorybook":0,"aliases":["--neem-lighter","--success-lighter"]},"--color-green-600":{"total":0,"fromImplementation":0,"fromStorybook":0,"aliases":[]},"--color-green-700":{"total":2,"fromImplementation":2,"fromStorybook":0,"aliases":["--neem-light","--success-light"]},"--color-green-800":{"total":0,"fromImplementation":0,"fromStorybook":0,"aliases":[]},"--color-green-900":{"total":0,"fromImplementation":0,"fromStorybook":0,"aliases":[]},"--color-indigo-100":{"total":1,"fromImplementation":1,"fromStorybook":0,"aliases":["--accent3-ultra-light"]},"--color-indigo-1000":{"total":11,"fromImplementation":11,"fromStorybook":0,"aliases":["--accent3","--accent3-shadow","--neel"]},"--color-indigo-1000-16a":{"total":0,"fromImplementation":0,"fromStorybook":0,"aliases":[]},"--color-indigo-1100":{"total":0,"fromImplementation":0,"fromStorybook":0,"aliases":[]},"--color-indigo-1200":{"total":3,"fromImplementation":3,"fromStorybook":0,"aliases":["--accent3-dark","--neel-dark"]},"--color-indigo-1300":{"total":0,"fromImplementation":0,"fromStorybook":0,"aliases":[]},"--color-indigo-1400":{"total":5,"fromImplementation":5,"fromStorybook":0,"aliases":["--accent3-darker","--neel-darker"]},"--color-indigo-200":{"total":4,"fromImplementation":4,"fromStorybook":0,"aliases":["--accent3-lightest","--neel-lightest"]},"--color-indigo-300":{"total":1,"fromImplementation":1,"fromStorybook":0,"aliases":["--accent3-300"]},"--color-indigo-400":{"total":0,"fromImplementation":0,"fromStorybook":0,"aliases":[]},"--color-indigo-500":{"total":3,"fromImplementation":3,"fromStorybook":0,"aliases":["--accent3-lighter","--neel-lighter"]},"--color-indigo-600":{"total":0,"fromImplementation":0,"fromStorybook":0,"aliases":[]},"--color-indigo-700":{"total":2,"fromImplementation":2,"fromStorybook":0,"aliases":["--accent3-light","--neel-light"]},"--color-indigo-800":{"total":0,"fromImplementation":0,"fromStorybook":0,"aliases":[]},"--color-indigo-900":{"total":0,"fromImplementation":0,"fromStorybook":0,"aliases":[]},"--color-lime-100":{"total":1,"fromImplementation":1,"fromStorybook":0,"aliases":["--accent4-ultra-light"]},"--color-lime-1000":{"total":0,"fromImplementation":0,"fromStorybook":0,"aliases":[]},"--color-lime-1000-16a":{"total":0,"fromImplementation":0,"fromStorybook":0,"aliases":[]},"--color-lime-1100":{"total":3,"fromImplementation":3,"fromStorybook":0,"aliases":["--accent4-dark","--nimbu-dark"]},"--color-lime-1200":{"total":0,"fromImplementation":0,"fromStorybook":0,"aliases":[]},"--color-lime-1300":{"total":6,"fromImplementation":6,"fromStorybook":0,"aliases":["--accent4-darker","--nimbu-darker"]},"--color-lime-1400":{"total":0,"fromImplementation":0,"fromStorybook":0,"aliases":[]},"--color-lime-200":{"total":3,"fromImplementation":3,"fromStorybook":0,"aliases":["--accent4-lightest","--nimbu-lightest"]},"--color-lime-300":{"total":1,"fromImplementation":1,"fromStorybook":0,"aliases":["--accent4-300"]},"--color-lime-400":{"total":0,"fromImplementation":0,"fromStorybook":0,"aliases":[]},"--color-lime-500":{"total":3,"fromImplementation":3,"fromStorybook":0,"aliases":["--accent4-lighter","--nimbu-lighter"]},"--color-lime-600":{"total":0,"fromImplementation":0,"fromStorybook":0,"aliases":[]},"--color-lime-700":{"total":2,"fromImplementation":2,"fromStorybook":0,"aliases":["--accent4-light","--nimbu-light"]},"--color-lime-800":{"total":0,"fromImplementation":0,"fromStorybook":0,"aliases":[]},"--color-lime-900":{"total":10,"fromImplementation":10,"fromStorybook":0,"aliases":["--accent4","--accent4-shadow","--nimbu"]},"--color-lime-900-16a":{"total":0,"fromImplementation":0,"fromStorybook":0,"aliases":[]},"--color-magenta-100":{"total":0,"fromImplementation":0,"fromStorybook":0,"aliases":[]},"--color-magenta-1000":{"total":0,"fromImplementation":0,"fromStorybook":0,"aliases":[]},"--color-magenta-1100":{"total":0,"fromImplementation":0,"fromStorybook":0,"aliases":[]},"--color-magenta-1200":{"total":0,"fromImplementation":0,"fromStorybook":0,"aliases":[]},"--color-magenta-1300":{"total":0,"fromImplementation":0,"fromStorybook":0,"aliases":[]},"--color-magenta-1400":{"total":0,"fromImplementation":0,"fromStorybook":0,"aliases":[]},"--color-magenta-200":{"total":0,"fromImplementation":0,"fromStorybook":0,"aliases":[]},"--color-magenta-300":{"total":0,"fromImplementation":0,"fromStorybook":0,"aliases":[]},"--color-magenta-400":{"total":0,"fromImplementation":0,"fromStorybook":0,"aliases":[]},"--color-magenta-500":{"total":0,"fromImplementation":0,"fromStorybook":0,"aliases":[]},"--color-magenta-600":{"total":0,"fromImplementation":0,"fromStorybook":0,"aliases":[]},"--color-magenta-700":{"total":0,"fromImplementation":0,"fromStorybook":0,"aliases":[]},"--color-magenta-800":{"total":0,"fromImplementation":0,"fromStorybook":0,"aliases":[]},"--color-magenta-900":{"total":0,"fromImplementation":0,"fromStorybook":0,"aliases":[]},"--color-orange-100":{"total":1,"fromImplementation":1,"fromStorybook":0,"aliases":["--accent1-ultra-light"]},"--color-orange-1000":{"total":13,"fromImplementation":13,"fromStorybook":0,"aliases":["--accent1","--accent1-shadow","--tawak"]},"--color-orange-1000-16a":{"total":0,"fromImplementation":0,"fromStorybook":0,"aliases":[]},"--color-orange-1000-4a":{"total":0,"fromImplementation":0,"fromStorybook":0,"aliases":[]},"--color-orange-1100":{"total":0,"fromImplementation":0,"fromStorybook":0,"aliases":[]},"--color-orange-1200":{"total":5,"fromImplementation":5,"fromStorybook":0,"aliases":["--accent1-dark","--tawak-dark"]},"--color-orange-1300":{"total":6,"fromImplementation":6,"fromStorybook":0,"aliases":["--accent1-darker","--tawak-darker"]},"--color-orange-1400":{"total":0,"fromImplementation":0,"fromStorybook":0,"aliases":[]},"--color-orange-200":{"total":4,"fromImplementation":4,"fromStorybook":0,"aliases":["--accent1-lightest","--tawak-lightest"]},"--color-orange-300":{"total":1,"fromImplementation":1,"fromStorybook":0,"aliases":["--accent1-300"]},"--color-orange-400":{"total":0,"fromImplementation":0,"fromStorybook":0,"aliases":[]},"--color-orange-500":{"total":3,"fromImplementation":3,"fromStorybook":0,"aliases":["--accent1-lighter","--tawak-lighter"]},"--color-orange-600":{"total":0,"fromImplementation":0,"fromStorybook":0,"aliases":[]},"--color-orange-700":{"total":2,"fromImplementation":2,"fromStorybook":0,"aliases":["--accent1-light","--tawak-light"]},"--color-orange-800":{"total":0,"fromImplementation":0,"fromStorybook":0,"aliases":[]},"--color-orange-900":{"total":0,"fromImplementation":0,"fromStorybook":0,"aliases":[]},"--color-pink-100":{"total":0,"fromImplementation":0,"fromStorybook":0,"aliases":[]},"--color-pink-1000":{"total":0,"fromImplementation":0,"fromStorybook":0,"aliases":[]},"--color-pink-1100":{"total":0,"fromImplementation":0,"fromStorybook":0,"aliases":[]},"--color-pink-1200":{"total":0,"fromImplementation":0,"fromStorybook":0,"aliases":[]},"--color-pink-1300":{"total":0,"fromImplementation":0,"fromStorybook":0,"aliases":[]},"--color-pink-1400":{"total":0,"fromImplementation":0,"fromStorybook":0,"aliases":[]},"--color-pink-200":{"total":0,"fromImplementation":0,"fromStorybook":0,"aliases":[]},"--color-pink-300":{"total":0,"fromImplementation":0,"fromStorybook":0,"aliases":[]},"--color-pink-400":{"total":0,"fromImplementation":0,"fromStorybook":0,"aliases":[]},"--color-pink-500":{"total":0,"fromImplementation":0,"fromStorybook":0,"aliases":[]},"--color-pink-600":{"total":0,"fromImplementation":0,"fromStorybook":0,"aliases":[]},"--color-pink-700":{"total":0,"fromImplementation":0,"fromStorybook":0,"aliases":[]},"--color-pink-800":{"total":0,"fromImplementation":0,"fromStorybook":0,"aliases":[]},"--color-pink-900":{"total":0,"fromImplementation":0,"fromStorybook":0,"aliases":[]},"--color-red-100":{"total":2,"fromImplementation":2,"fromStorybook":0,"aliases":["--alert-ultra-light"]},"--color-red-1000":{"total":75,"fromImplementation":74,"fromStorybook":1,"aliases":["--alert","--alert-shadow","--mirch","--text-destructive"]},"--color-red-1000-16a":{"total":0,"fromImplementation":0,"fromStorybook":0,"aliases":[]},"--color-red-1000-4a":{"total":0,"fromImplementation":0,"fromStorybook":0,"aliases":[]},"--color-red-1100":{"total":0,"fromImplementation":0,"fromStorybook":0,"aliases":[]},"--color-red-1200":{"total":15,"fromImplementation":15,"fromStorybook":0,"aliases":["--alert-dark","--mirch-dark"]},"--color-red-1200-16a":{"total":0,"fromImplementation":0,"fromStorybook":0,"aliases":[]},"--color-red-1300":{"total":12,"fromImplementation":12,"fromStorybook":0,"aliases":["--alert-darker","--mirch-darker"]},"--color-red-1400":{"total":0,"fromImplementation":0,"fromStorybook":0,"aliases":[]},"--color-red-200":{"total":13,"fromImplementation":13,"fromStorybook":0,"aliases":["--alert-lightest","--mirch-lightest"]},"--color-red-300":{"total":1,"fromImplementation":1,"fromStorybook":0,"aliases":["--alert-300"]},"--color-red-400":{"total":0,"fromImplementation":0,"fromStorybook":0,"aliases":[]},"--color-red-500":{"total":10,"fromImplementation":10,"fromStorybook":0,"aliases":["--alert-lighter","--mirch-lighter"]},"--color-red-600":{"total":0,"fromImplementation":0,"fromStorybook":0,"aliases":[]},"--color-red-700":{"total":2,"fromImplementation":2,"fromStorybook":0,"aliases":["--alert-light","--mirch-light"]},"--color-red-800":{"total":0,"fromImplementation":0,"fromStorybook":0,"aliases":[]},"--color-red-900":{"total":0,"fromImplementation":0,"fromStorybook":0,"aliases":[]},"--color-sea-100":{"total":0,"fromImplementation":0,"fromStorybook":0,"aliases":[]},"--color-sea-1000":{"total":0,"fromImplementation":0,"fromStorybook":0,"aliases":[]},"--color-sea-1100":{"total":0,"fromImplementation":0,"fromStorybook":0,"aliases":[]},"--color-sea-1200":{"total":0,"fromImplementation":0,"fromStorybook":0,"aliases":[]},"--color-sea-1300":{"total":0,"fromImplementation":0,"fromStorybook":0,"aliases":[]},"--color-sea-1400":{"total":0,"fromImplementation":0,"fromStorybook":0,"aliases":[]},"--color-sea-200":{"total":0,"fromImplementation":0,"fromStorybook":0,"aliases":[]},"--color-sea-300":{"total":0,"fromImplementation":0,"fromStorybook":0,"aliases":[]},"--color-sea-400":{"total":0,"fromImplementation":0,"fromStorybook":0,"aliases":[]},"--color-sea-500":{"total":0,"fromImplementation":0,"fromStorybook":0,"aliases":[]},"--color-sea-600":{"total":0,"fromImplementation":0,"fromStorybook":0,"aliases":[]},"--color-sea-700":{"total":0,"fromImplementation":0,"fromStorybook":0,"aliases":[]},"--color-sea-800":{"total":0,"fromImplementation":0,"fromStorybook":0,"aliases":[]},"--color-sea-900":{"total":0,"fromImplementation":0,"fromStorybook":0,"aliases":[]},"--color-violet-100":{"total":1,"fromImplementation":1,"fromStorybook":0,"aliases":["--accent2-ultra-light"]},"--color-violet-1000":{"total":11,"fromImplementation":11,"fromStorybook":0,"aliases":["--accent2","--accent2-shadow","--jamun"]},"--color-violet-1000-16a":{"total":0,"fromImplementation":0,"fromStorybook":0,"aliases":[]},"--color-violet-1100":{"total":0,"fromImplementation":0,"fromStorybook":0,"aliases":[]},"--color-violet-1200":{"total":3,"fromImplementation":3,"fromStorybook":0,"aliases":["--accent2-dark","--jamun-dark"]},"--color-violet-1300":{"total":0,"fromImplementation":0,"fromStorybook":0,"aliases":[]},"--color-violet-1400":{"total":5,"fromImplementation":5,"fromStorybook":0,"aliases":["--accent2-darker","--jamun-darker"]},"--color-violet-200":{"total":4,"fromImplementation":4,"fromStorybook":0,"aliases":["--accent2-lightest","--jamun-lightest"]},"--color-violet-300":{"total":1,"fromImplementation":1,"fromStorybook":0,"aliases":["--accent2-300"]},"--color-violet-400":{"total":0,"fromImplementation":0,"fromStorybook":0,"aliases":[]},"--color-violet-500":{"total":3,"fromImplementation":3,"fromStorybook":0,"aliases":["--accent2-lighter","--jamun-lighter"]},"--color-violet-600":{"total":0,"fromImplementation":0,"fromStorybook":0,"aliases":[]},"--color-violet-700":{"total":2,"fromImplementation":2,"fromStorybook":0,"aliases":["--accent2-light","--jamun-light"]},"--color-violet-800":{"total":0,"fromImplementation":0,"fromStorybook":0,"aliases":[]},"--color-violet-900":{"total":0,"fromImplementation":0,"fromStorybook":0,"aliases":[]},"--color-white":{"total":62,"fromImplementation":61,"fromStorybook":1,"aliases":["--text-white","--white"]},"--color-white-48a":{"total":0,"fromImplementation":0,"fromStorybook":0,"aliases":[]},"--color-white-80a":{"total":0,"fromImplementation":0,"fromStorybook":0,"aliases":[]},"--color-yellow-100":{"total":1,"fromImplementation":1,"fromStorybook":0,"aliases":["--warning-ultra-light"]},"--color-yellow-1000":{"total":0,"fromImplementation":0,"fromStorybook":0,"aliases":[]},"--color-yellow-1000-16a":{"total":0,"fromImplementation":0,"fromStorybook":0,"aliases":[]},"--color-yellow-1100":{"total":5,"fromImplementation":5,"fromStorybook":0,"aliases":["--haldi-dark","--warning-dark"]},"--color-yellow-1100-16a":{"total":0,"fromImplementation":0,"fromStorybook":0,"aliases":[]},"--color-yellow-1200":{"total":0,"fromImplementation":0,"fromStorybook":0,"aliases":[]},"--color-yellow-1300":{"total":9,"fromImplementation":9,"fromStorybook":0,"aliases":["--haldi-darker","--warning-darker"]},"--color-yellow-1400":{"total":0,"fromImplementation":0,"fromStorybook":0,"aliases":[]},"--color-yellow-200":{"total":3,"fromImplementation":3,"fromStorybook":0,"aliases":["--haldi-lightest","--warning-lightest"]},"--color-yellow-300":{"total":1,"fromImplementation":1,"fromStorybook":0,"aliases":["--warning-300"]},"--color-yellow-400":{"total":0,"fromImplementation":0,"fromStorybook":0,"aliases":[]},"--color-yellow-500":{"total":3,"fromImplementation":3,"fromStorybook":0,"aliases":["--haldi-lighter","--warning-lighter"]},"--color-yellow-600":{"total":0,"fromImplementation":0,"fromStorybook":0,"aliases":[]},"--color-yellow-700":{"total":4,"fromImplementation":4,"fromStorybook":0,"aliases":["--haldi-light","--warning-light"]},"--color-yellow-800":{"total":0,"fromImplementation":0,"fromStorybook":0,"aliases":[]},"--color-yellow-900":{"total":34,"fromImplementation":33,"fromStorybook":1,"aliases":["--haldi","--warning","--warning-shadow"]},"--color-yellow-900-16a":{"total":0,"fromImplementation":0,"fromStorybook":0,"aliases":[]},"--color-yellow-900-4a":{"total":0,"fromImplementation":0,"fromStorybook":0,"aliases":[]}}}